[
  {
    "title": "Computer & Laptop",
    "subcategories": [
      "PCs",
      "Laptops",
      "PC Komponenten",
      "Server",
      "Netzwerk",
      "Mac",
      "Software",
      "Zubehör"
    ]
  },
  {
    "title": "Smartphone & Tablet",
    "subcategories": [
      "Android Smartphones",
      "iPhones",
      "Windows Phones",
      "Android Tablets",
      "iPads",
      "Windows Tablets",
      "Handys"
    ]
  },
  {
    "title": "Fernseher",
    "subcategories": [
      "TVs",
      "Beamer",
      "DVD & Blu-ray",
      "Empfangstechnik",
      "Kabel & Adapter",
      "Zubehör"
    ]
  },
  {
    "title": "Haushalt",
    "subcategories": [
      "Küchengeräte",
      "Reinigen",
      "Beleuchtung",
      "Garten",
      "Sicherheitstechnik",
      "Stromversorgung",
      "Heizen & Klima",
      "Werkzeug"
    ]
  },
  { "title": "Kamera", "subcategories": ["Foto", "Video", "Dronen"] },
  {
    "title": "Audio",
    "subcategories": [
      "HiFi-Anlagen",
      "Kopfhörer",
      "Lautsprecher",
      "Kabel & Adapter",
      "Zubehör"
    ]
  },
  {
    "title": "Spielzeug",
    "subcategories": [
      "Spielekonsolen",
      "Gesellschaftsspiele",
      "Ferngesteuerte Modelle",
      "Kinderspielzeug",
      "Lernspiele"
    ]
  },
  {
    "title": "Outdoor",
    "subcategories": ["Zelten & Camping", "Boote", "Wandern", "E-Bikes"]
  }
]
